{"cameraMode":{"drawMode":0,"name":"Shaded","section":"Shading Mode"},"sceneLighting":true,"audioPlay":false,"sceneViewState":{"showFog":true,"showMaterialUpdate":false,"showSkybox":true,"showFlares":true,"showImageEffects":true,"showParticleSystems":true},"in2DMode":false,"pivot":{"x":-3.3149867057800295,"y":6.09455680847168,"z":6.421600818634033},"rotation":{"x":-0.28401118516921999,"y":0.3427639901638031,"z":-0.10953604429960251,"w":-0.8887364268302918},"size":17.147300720214845,"orthographic":false}